[
  {
    "name": "PC端",
    "name_en": "pc",
    "code": "100000",
    "api_codes": [],
    "children": [
      {
        "name": "首页",
        "name_en": "home",
        "code": "110000",
        "platform": 2,
        "children": [
          {
            "name": "数据简报",
            "name_en": "dataOverview",
            "code": "111000",
            "children": [
              {
                "name": "数据查看",
                "name_en": "saleGoalShow",
                "code": "111100"
              },
              {
                "name": "设置目标",
                "name_en": "saleGoalSet",
                "code": "111200"
              }
            ]
          }
        ]
      },
      {
        "name": "销售业务",
        "name_en": "sale",
        "code": "120000",
        "children": [
          {
            "name": "客户",
            "name_en": "customer",
            "code": "121000",
            "children": [
              {
                "name": "客户",
                "name_en": "customerList",
                "code": "121100",
                "children": [
                  {
                    "name": "新建客户",
                    "name_en": "customerNew",
                    "code": "121101",
                    "api_codes": [
                      "602"
                    ]
                  },
                  {
                    "name": "编辑客户",
                    "name_en": "customerEdit",
                    "code": "121102",
                    "api_codes": [
                      "603"
                    ]
                  },
                  {
                    "name": "客户导入导出",
                    "name_en": "customerIE",
                    "code": "121103"
                  },
                  {
                    "name": "客户批量操作",
                    "name_en": "customerBatchAction",
                    "code": "121104"
                  },
                  {
                    "name": "客户转移",
                    "name_en": "customerTransfer",
                    "code": "121105"
                  },
                  {
                    "name": "客户详情",
                    "name_en": "customerShow",
                    "code": "121106",
                    "api_codes": [
                      "601"
                    ],
                    "children": [
                      {
                        "name": "总览",
                        "name_en": "customerOverview",
                        "code": "121107",
                        "platform": 2
                      },
                      {
                        "name": "客户设备",
                        "name_en": "customerDeviceList",
                        "code": "121108",
                        "children": [
                          {
                            "name": "添加设备",
                            "name_en": "customerDeviceNew",
                            "code": "121109"
                          },
                          {
                            "name": "编辑设备",
                            "name_en": "customerDeviceEdit",
                            "code": "121110"
                          },
                          {
                            "name": "维护到SAP",
                            "name_en": "customerDeviceSAP",
                            "code": "121111"
                          },
                          {
                            "name": "导出设备",
                            "name_en": "customerDeviceIE",
                            "code": "121112"
                          }
                        ]
                      },
                      {
                        "name": "收款记录",
                        "name_en": "customerCollectionList",
                        "code": "121113",
                        "platform": 2,
                        "children": [
                          {
                            "name": "添加回款记录",
                            "name_en": "customerCollectionNew",
                            "code": "121114",
                            "platform": 2
                          }
                        ]
                      },
                      {
                        "name": "费用流水",
                        "name_en": "customerFeeList",
                        "code": "121115",
                        "platform": 2
                      },
                      {
                        "name": "拜访记录",
                        "name_en": "customerFollowUpList",
                        "code": "121116",
                        "children": [
                          {
                            "name": "添加拜访记录",
                            "name_en": "customerFollowUpNew",
                            "code": "121117"
                          }
                        ]
                      },
                      {
                        "name": "联系人管理",
                        "name_en": "customerContactorList",
                        "code": "121118",
                        "children": [
                          {
                            "name": "添加联系人",
                            "name_en": "customerContactorNew",
                            "code": "121119"
                          },
                          {
                            "name": "编辑联系人",
                            "name_en": "customerContactorEdit",
                            "code": "121120"
                          },
                          {
                            "name": "删除联系人",
                            "name_en": "customerContactorDelete",
                            "code": "121121"
                          }
                        ]
                      },
                      {
                        "name": "发票管理",
                        "name_en": "customerInvoiceList",
                        "code": "121122",
                        "children": [
                          {
                            "name": "添加发票",
                            "name_en": "customerInvoiceNew",
                            "code": "121123"
                          },
                          {
                            "name": "编辑发票",
                            "name_en": "customerInvoiceEdit",
                            "code": "121124"
                          }
                        ]
                      }
                    ]
                  }
                ]
              },
              {
                "name": "中间商",
                "name_en": "dealerList",
                "platform": 1,
                "code": "121200",
                "api_codes": [],
                "children": [
                  {
                    "name": "新建中间商",
                    "name_en": "dealerNew",
                    "code": "121201"
                  },
                  {
                    "name": "编辑中间商",
                    "name_en": "dealerEdit",
                    "code": "121202"
                  },
                  {
                    "name": "状态切换",
                    "name_en": "dealerStatus",
                    "code": "121203"
                  },
                  {
                    "name": "中间商详情",
                    "name_en": "dealerShow",
                    "code": "121204",
                    "children": [
                      {
                        "name": "客户",
                        "name_en": "dealerCustomer",
                        "code": "121205"
                      },
                      {
                        "name": "设备",
                        "name_en": "dealerDevice",
                        "code": "121206"
                      },
                      {
                        "name": "人员",
                        "name_en": "dealerUser",
                        "code": "121207"
                      },
                      {
                        "name": "设置",
                        "name_en": "dealerSetting",
                        "code": "121208"
                      }
                    ]
                  }
                ]
              }
            ]
          },
          {
            "name": "订单",
            "name_en": "order",
            "code": "122000",
            "platform": 2,
            "children": [
              {
                "name": "订单",
                "name_en": "orderList",
                "code": "122100",
                "platform": 2,
                "children": [
                  {
                    "name": "添加订单",
                    "name_en": "orderNew",
                    "code": "122101",
                    "platform": 2
                  },
                  {
                    "name": "编辑订单",
                    "name_en": "orderEdit",
                    "code": "122102",
                    "platform": 2
                  },
                  {
                    "name": "删除订单",
                    "name_en": "orderDelete",
                    "code": "122103",
                    "platform": 2
                  },
                  {
                    "name": "导出订单",
                    "name_en": "orderIE",
                    "code": "122104",
                    "platform": 2
                  },
                  {
                    "name": "订单详情",
                    "name_en": "orderShow",
                    "code": "122105",
                    "platform": 2,
                    "children": [
                      {
                        "name": "订单合同审核",
                        "name_en": "orderApprove",
                        "code": "122106",
                        "platform": 2
                      },
                      {
                        "name": "提交合同审批",
                        "name_en": "orderApplication",
                        "code": "122107",
                        "platform": 2
                      },
                      {
                        "name": "完成采购发货",
                        "name_en": "orderPurchase",
                        "code": "122108",
                        "platform": 2
                      },
                      {
                        "name": "完成实施安装",
                        "name_en": "orderInstall",
                        "code": "122109",
                        "platform": 2
                      },
                      {
                        "name": "总览",
                        "name_en": "orderOverview",
                        "code": "122110",
                        "platform": 2
                      },
                      {
                        "name": "合同",
                        "name_en": "orderAgreement",
                        "code": "122111",
                        "platform": 2,
                        "children": [
                          {
                            "name": "添加合同",
                            "name_en": "orderAgreementNew",
                            "code": "122112",
                            "platform": 2
                          },
                          {
                            "name": "查看合同",
                            "name_en": "orderAgreementShow",
                            "code": "122113",
                            "platform": 2
                          },
                          {
                            "name": "下载合同",
                            "name_en": "orderAgreementDownload",
                            "code": "122114",
                            "platform": 2
                          }
                        ]
                      },
                      {
                        "name": "采购/发货",
                        "name_en": "orderPurchase",
                        "code": "122115",
                        "platform": 2,
                        "children": [
                          {
                            "name": "添加采购单",
                            "name_en": "orderPurchaseNew",
                            "code": "122116",
                            "platform": 2
                          },
                          {
                            "name": "添加发货",
                            "name_en": "orderShipNew",
                            "code": "122117",
                            "platform": 2
                          }
                        ]
                      },
                      {
                        "name": "回款/费用",
                        "name_en": "orderFee",
                        "code": "122118",
                        "platform": 2,
                        "children": [
                          {
                            "name": "添加回款",
                            "name_en": "orderPayBackNew",
                            "code": "122119",
                            "platform": 2
                          },
                          {
                            "name": "编辑回款",
                            "name_en": "orderPayBackEdit",
                            "code": "122120",
                            "platform": 2
                          },
                          {
                            "name": "删除回款",
                            "name_en": "orderPayBackDelete",
                            "code": "122121",
                            "platform": 2
                          },
                          {
                            "name": "添加费用",
                            "name_en": "orderExpenseNew",
                            "code": "122122",
                            "platform": 2
                          },
                          {
                            "name": "编辑费用",
                            "name_en": "orderExpenseEdit",
                            "code": "122123",
                            "platform": 2
                          },
                          {
                            "name": "删除费用",
                            "name_en": "orderExpenseDelete",
                            "code": "122124",
                            "platform": 2
                          }
                        ]
                      },
                      {
                        "name": "开票记录",
                        "name_en": "orderInvoiceRecordList",
                        "code": "122125",
                        "platform": 2,
                        "children": [
                          {
                            "name": "添加开票记录",
                            "name_en": "orderInvoiceRecordNew",
                            "code": "122126",
                            "platform": 2
                          },
                          {
                            "name": "编辑开票记录",
                            "name_en": "orderInvoiceRecordEdit",
                            "code": "122127",
                            "platform": 2
                          },
                          {
                            "name": "删除开票记录",
                            "name_en": "orderInvoiceRecordDelete",
                            "code": "122128",
                            "platform": 2
                          }
                        ]
                      },
                      {
                        "name": "操作记录",
                        "name_en": "orderLog",
                        "code": "122129",
                        "platform": 2
                      }
                    ]
                  }
                ]
              },
              {
                "name": "报价单",
                "name_en": "quotationList",
                "code": "122200",
                "platform": 2,
                "children": [
                  {
                    "name": "添加报价单",
                    "name_en": "quotationNew",
                    "code": "122201"
                  },
                  {
                    "name": "编辑报价单",
                    "name_en": "quotationEdit",
                    "code": "122202"
                  },
                  {
                    "name": "删除报价单",
                    "name_en": "quotationDelete",
                    "code": "122203"
                  },
                  {
                    "name": "报价单详情",
                    "name_en": "quotationShow",
                    "code": "122204"
                  },
                  {
                    "name": "报价单审核",
                    "name_en": "quotationApprove",
                    "code": "122205"
                  }
                ]
              },
              {
                "name": "采购单",
                "name_en": "purchaseOrderList",
                "code": "122300",
                "platform": 2,
                "children": [
                  {
                    "name": "采购单导出",
                    "name_en": "purchaseOrderIE",
                    "code": "122301"
                  },
                  {
                    "name": "添加采购单",
                    "name_en": "purchaseOrderNew",
                    "code": "122302"
                  },
                  {
                    "name": "编辑采购单",
                    "name_en": "purchaseOrderEdit",
                    "code": "122303"
                  },
                  {
                    "name": "删除采购单",
                    "name_en": "purchaseOrderDelete",
                    "code": "122304"
                  },
                  {
                    "name": "采购单详情",
                    "name_en": "purchaseOrderShow",
                    "code": "122305"
                  },
                  {
                    "name": "采购单审批",
                    "name_en": "purchaseOrderApprove",
                    "code": "122306"
                  }
                ]
              }
            ]
          }
        ]
      },
      {
        "name": "库存管理",
        "name_en": "store",
        "platform": 2,
        "code": "130000",
        "children": [
          {
            "name": "库存",
            "name_en": "store",
            "platform": 2,
            "code": "131000",
            "children": [
              {
                "name": "入库管理",
                "name_en": "stockInList",
                "platform": 2,
                "code": "131100",
                "children": [
                  {
                    "name": "添加入库",
                    "name_en": "stockInNew",
                    "code": "131101"
                  },
                  {
                    "name": "编辑入库",
                    "name_en": "stockInEdit",
                    "code": "131102"
                  },
                  {
                    "name": "删除入库",
                    "name_en": "stockInDelete",
                    "code": "131103"
                  },
                  {
                    "name": "确认入库",
                    "name_en": "stockInCheck",
                    "code": "131104"
                  }
                ]
              },
              {
                "name": "出库管理",
                "name_en": "stockOutList",
                "platform": 2,
                "code": "131200",
                "children": [
                  {
                    "name": "添加出库",
                    "name_en": "stockOutNew",
                    "code": "131201"
                  },
                  {
                    "name": "编辑出库",
                    "name_en": "stockOutEdit",
                    "code": "131202"
                  },
                  {
                    "name": "删除出库",
                    "name_en": "stockOutDelete",
                    "code": "131203"
                  },
                  {
                    "name": "确认出库",
                    "name_en": "stockOutCheck",
                    "code": "131204"
                  }
                ]
              },
              {
                "name": "库存状态",
                "name_en": "storeItemList",
                "platform": 2,
                "code": "131300"
              },
              {
                "name": "仓库设置",
                "name_en": "stockroomList",
                "platform": 2,
                "code": "131400",
                "children": [
                  {
                    "name": "添加仓库",
                    "name_en": "stockroomNew",
                    "code": "131401"
                  },
                  {
                    "name": "编辑仓库",
                    "name_en": "stockroomEdit",
                    "code": "131402"
                  },
                  {
                    "name": "删除仓库",
                    "name_en": "stockroomDelete",
                    "code": "131403"
                  }
                ]
              }
            ]
          },
          {
            "name": "产品",
            "name_en": "product",
            "code": "132000",
            "api_codes": [],
            "children": [
              {
                "name": "供应商",
                "name_en": "supplierList",
                "platform": 2,
                "code": "132100",
                "children": [
                  {
                    "name": "添加供应商",
                    "name_en": "supplierNew",
                    "code": "132101"
                  },
                  {
                    "name": "编辑供应商",
                    "name_en": "supplierEdit",
                    "code": "132102"
                  },
                  {
                    "name": "删除供应商",
                    "name_en": "supplierDelete",
                    "code": "132103"
                  }
                ]
              },
              {
                "name": "产品分类",
                "name_en": "productCategoryList",
                "code": "132200",
                "api_codes": [],
                "children": [
                  {
                    "name": "零件分类",
                    "name_en": "itemCategoryList",
                    "platform": 2,
                    "code": "132201",
                    "children": [
                      {
                        "name": "添加分类",
                        "name_en": "itemCategoryNew",
                        "platform": 2,
                        "code": "132202"
                      },
                      {
                        "name": "编辑分类",
                        "name_en": "itemCategoryEdit",
                        "platform": 2,
                        "code": "132203"
                      },
                      {
                        "name": "删除分类",
                        "name_en": "itemCategoryDelete",
                        "platform": 2,
                        "code": "132204"
                      }
                    ]
                  },
                  {
                    "name": "设备分类",
                    "name_en": "deviceCategoryList",
                    "code": "132205",
                    "children": [
                      {
                        "name": "添加分类",
                        "name_en": "deviceCategoryNew",
                        "code": "132206"
                      },
                      {
                        "name": "编辑分类",
                        "name_en": "deviceCategoryEdit",
                        "code": "132207"
                      },
                      {
                        "name": "删除分类",
                        "name_en": "deviceCategoryDelete",
                        "code": "132208"
                      }
                    ]
                  }
                ]
              },
              {
                "name": "产品库",
                "name_en": "productList",
                "code": "132300",
                "platform": 2,
                "children": [
                  {
                    "name": "产品导出导入",
                    "name_en": "productIE",
                    "code": "132301"
                  },
                  {
                    "name": "添加产品",
                    "name_en": "productNew",
                    "code": "132302"
                  },
                  {
                    "name": "编辑产品",
                    "name_en": "productEdit",
                    "code": "132303"
                  },
                  {
                    "name": "删除产品",
                    "name_en": "productDelete",
                    "code": "132304"
                  }
                ]
              }
            ]
          }
        ]
      },
      {
        "name": "统计",
        "name_en": "statistics",
        "code": "140000",
        "children": [
          {
            "name": "统计",
            "name_en": "statistic",
            "code": "141000",
            "api_codes": [],
            "children": [
              {
                "name": "设备数据维护",
                "name_en": "effectiveDeviceList",
                "code": "141100",
                "api_codes": []
              },
              {
                "name": "销售报表",
                "name_en": "saleReport",
                "code": "141200",
                "platform": 2,
                "api_codes": [],
                "children": [
                  {
                    "name": "客户覆盖",
                    "name_en": "customerCoverage",
                    "platform": 2,
                    "code": "141201",
                    "api_codes": []
                  },
                  {
                    "name": "报价转化",
                    "name_en": "quotationConversion",
                    "code": "141202",
                    "platform": 2,
                    "api_codes": []
                  }
                ]
              }
            ]
          }
        ]
      },
      {
        "name": "系统管理",
        "name_en": "systemManage",
        "code": "150000",
        "children": [
          {
            "name": "管理中心",
            "name_en": "setting",
            "code": "151000",
            "api_codes": [],
            "children": [
              {
                "name": "人员管理",
                "name_en": "userList",
                "code": "151100",
                "platform": 1,
                "api_codes": [],
                "children": [
                  {
                    "name": "添加人员",
                    "name_en": "userNew",
                    "code": "151101"
                  },
                  {
                    "name": "编辑人员",
                    "name_en": "userEdit",
                    "code": "151102"
                  },
                  {
                    "name": "人员状态管理",
                    "name_en": "userStatus",
                    "code": "151103"
                  }
                ]
              },
              {
                "name": "人员管理",
                "name_en": "dealerUserList",
                "code": "151200",
                "platform": 2,
                "api_codes": [],
                "children": [
                  {
                    "name": "添加人员",
                    "name_en": "dealerUserNew",
                    "code": "151201"
                  },
                  {
                    "name": "编辑人员",
                    "name_en": "dealerUserEdit",
                    "code": "151202"
                  },
                  {
                    "name": "人员状态管理",
                    "name_en": "dealerUserStatus",
                    "code": "151203"
                  }
                ]
              },
              {
                "name": "角色管理",
                "name_en": "roleList",
                "code": "151300",
                "children": [
                  {
                    "name": "增加角色",
                    "name_en": "roleNew",
                    "code": "151301"
                  },
                  {
                    "name": "编辑角色",
                    "name_en": "roleEdit",
                    "code": "151302"
                  },
                  {
                    "name": "状态管理",
                    "name_en": "roleStatus",
                    "code": "151303"
                  },
                  {
                    "name": "删除角色",
                    "name_en": "roleDelete",
                    "code": "151304"
                  }
                ]
              },
              {
                "name": "资源权限管理",
                "name_en": "resourceSetting",
                "code": "151400"
              },
              {
                "name": "销售组管理",
                "name_en": "groupList",
                "code": "151500",
                "platform": 2,
                "children": [
                  {
                    "name": "添加销售组",
                    "name_en": "groupNew",
                    "code": "151501"
                  },
                  {
                    "name": "编辑销售组",
                    "name_en": "groupEdit",
                    "code": "151502"
                  },
                  {
                    "name": "删除销售组",
                    "name_en": "groupDelete",
                    "code": "151503"
                  }
                ]
              },
              {
                "name": "流程管理",
                "name_en": "flowList",
                "code": "151600",
                "platform": 2,
                "children": [
                  {
                    "name": "添加流程",
                    "name_en": "flowNew",
                    "code": "151601"
                  },
                  {
                    "name": "编辑流程",
                    "name_en": "flowEdit",
                    "code": "151602"
                  },
                  {
                    "name": "删除流程",
                    "name_en": "flowDelete",
                    "code": "151603"
                  }
                ]
              },
              {
                "name": "公司信息管理",
                "name_en": "dealerInfo",
                "code": "151700",
                "platform": 2
              }
            ]
          }
        ]
      }
    ]
  },
  {
    "name": "移动端",
    "name_en": "mobile",
    "code": "200000",
    "children": []
  }
]